gaussian_binomial_distribution_calculation/Binomialdistribution.py
gaussian_binomial_distribution_calculation/Gaussiandistribution.py
gaussian_binomial_distribution_calculation/Generaldistribution.py
gaussian_binomial_distribution_calculation/__init__.py
gaussian_binomial_distribution_calculation-1.0.2.dist-info/METADATA
gaussian_binomial_distribution_calculation-1.0.2.dist-info/WHEEL
gaussian_binomial_distribution_calculation-1.0.2.dist-info/top_level.txt
gaussian_binomial_distribution_calculation-1.0.2.dist-info/RECORD
