Metadata-Version: 2.1
Name: gaussian-binomial-distribution-calculation
Version: 1.0.2
Summary: Gaussian and Binomial distributions 
Home-page: UNKNOWN
Author: Paribesh Ranabhat
Author-email: paribessh_sab@hotmail.com
License: UNKNOWN
Platform: UNKNOWN
Classifier: Programming Language :: Python :: 3
Classifier: License :: OSI Approved :: MIT License
Classifier: Operating System :: OS Independent
Requires-Python: >=3.6
Requires-Dist: matplotlib
